{
    "biz": {
        "biz": "https://boards.4channel.org/biz/thread/58921935",
        "dd": "https://boards.4channel.org/biz/thread/58921489",
        "gme": "https://boards.4channel.org/biz/thread/58919353",
        "pmg": "https://boards.4channel.org/biz/thread/58914865",
        "smg": "https://boards.4channel.org/biz/thread/58903732",
        "tlcg": "https://boards.4channel.org/biz/thread/58912097",
        "wwg": "https://boards.4channel.org/biz/thread/58919522",
        "xmr": "https://boards.4channel.org/biz/thread/58904335",
        "xsg": "https://boards.4channel.org/biz/thread/58903741"
    },
    "ck": {
        "ctg": "https://boards.4channel.org/ck/thread/20788999",
        "wayern": "https://boards.4channel.org/ck/thread/20793147"
    },
    "fit": {
        "alpt": "https://boards.4channel.org/fit/thread/75010676",
        "dg": "https://boards.4channel.org/fit/thread/75009587",
        "fast": "https://boards.4channel.org/fit/thread/74985300",
        "fat": "https://boards.4channel.org/fit/thread/75010473",
        "fph": "https://boards.4channel.org/fit/thread/75013573",
        "fraud": "https://boards.4channel.org/fit/thread/75014762",
        "plg": "https://boards.4channel.org/fit/thread/75013578",
        "qtddtot": "https://boards.4channel.org/fit/thread/75013381",
        "run": "https://boards.4channel.org/fit/thread/75002755",
        "wmt": "https://boards.4channel.org/fit/thread/75014060"
    },
    "g": {
        "3": "https://boards.4channel.org/g/thread/102149552",
        "aad": "https://boards.4channel.org/g/thread/102151060",
        "aicg": "https://boards.4channel.org/g/thread/102161939",
        "c3g": "https://boards.4channel.org/g/thread/102161923",
        "cat": "https://boards.4channel.org/g/thread/102145645",
        "crt": "https://boards.4channel.org/g/thread/102150637",
        "csg": "https://boards.4channel.org/g/thread/102141466",
        "cyb": "https://boards.4channel.org/g/thread/102073366",
        "de3": "https://boards.4channel.org/g/thread/102143051",
        "dmp": "https://boards.4channel.org/g/thread/102131730",
        "dpt": "https://boards.4channel.org/g/thread/102147308",
        "fglt": "https://boards.4channel.org/g/thread/102151935",
        "fwt": "https://boards.4channel.org/g/thread/102150393",
        "g": "https://boards.4channel.org/g/thread/102142841",
        "gedg": "https://boards.4channel.org/g/thread/102150640",
        "gigachad": "https://boards.4channel.org/g/thread/102148761",
        "hsg": "https://boards.4channel.org/g/thread/102122157",
        "iemg": "https://boards.4channel.org/g/thread/102147686",
        "ifg": "https://boards.4channel.org/g/thread/102105985",
        "ldg": "https://boards.4channel.org/g/thread/102160057",
        "lmg": "https://boards.4channel.org/g/thread/102158049",
        "mkg": "https://boards.4channel.org/g/thread/102139728",
        "pcbg": "https://boards.4channel.org/g/thread/102160645",
        "ptg": "https://boards.4channel.org/g/thread/102153711",
        "sdg": "https://boards.4channel.org/g/thread/102157704",
        "spg": "https://boards.4channel.org/g/thread/102142195",
        "sqt": "https://boards.4channel.org/g/thread/102161915",
        "tpg": "https://boards.4channel.org/g/thread/102106455",
        "twg": "https://boards.4channel.org/g/thread/102144851",
        "wdg": "https://boards.4channel.org/g/thread/102088243"
    },
    "vg": {
        "1999": "https://boards.4channel.org/vg/thread/492400107",
        "2hug": "https://boards.4channel.org/vg/thread/490867608",
        "4ccg": "https://boards.4channel.org/vg/thread/492098034",
        "aa2g": "https://boards.4channel.org/vg/thread/492404340",
        "aceg": "https://boards.4channel.org/vg/thread/491639252",
        "afgg": "https://boards.4channel.org/vg/thread/490533875",
        "agdg": "https://boards.4channel.org/vg/thread/492493436",
        "aicg": "https://boards.4channel.org/vg/thread/492485597",
        "aids": "https://boards.4channel.org/vg/thread/492469223",
        "akg": "https://boards.4channel.org/vg/thread/492477675",
        "alg": "https://boards.4channel.org/vg/thread/492486435",
        "asg": "https://boards.4channel.org/vg/thread/492223039",
        "atg": "https://boards.4channel.org/vg/thread/492144870",
        "atgg": "https://boards.4channel.org/vg/thread/492430858",
        "axg": "https://boards.4channel.org/vg/thread/491603519",
        "bag": "https://boards.4channel.org/vg/thread/492465497",
        "bd2g": "https://boards.4channel.org/vg/thread/492247904",
        "bdog": "https://boards.4channel.org/vg/thread/491263634",
        "bgg": "https://boards.4channel.org/vg/thread/492471002",
        "bmw": "https://boards.4channel.org/vg/thread/492044590",
        "bowgen": "https://boards.4channel.org/vg/thread/492487208",
        "calg": "https://boards.4channel.org/vg/thread/492424348",
        "chess": "https://boards.4channel.org/vg/thread/492369467",
        "civ4xg": "https://boards.4channel.org/vg/thread/492129758",
        "codg": "https://boards.4channel.org/vg/thread/492344239",
        "coopg": "https://boards.4channel.org/vg/thread/492292010",
        "cp77g": "https://boards.4channel.org/vg/thread/492253810",
        "crpgg": "https://boards.4channel.org/vg/thread/492358278",
        "csg": "https://boards.4channel.org/vg/thread/492273948",
        "d2g": "https://boards.4channel.org/vg/thread/492352189",
        "d4g": "https://boards.4channel.org/vg/thread/492391058",
        "dbdg": "https://boards.4channel.org/vg/thread/492369586",
        "dbg": "https://boards.4channel.org/vg/thread/492445230",
        "ddg": "https://boards.4channel.org/vg/thread/492221979",
        "ddlc": "https://boards.4channel.org/vg/thread/491645570",
        "dg": "https://boards.4channel.org/vg/thread/492397242",
        "digi": "https://boards.4channel.org/vg/thread/492314060",
        "dlg": "https://boards.4channel.org/vg/thread/492427410",
        "dlsg": "https://boards.4channel.org/vg/thread/491977752",
        "dng": "https://boards.4channel.org/vg/thread/492448732",
        "domg": "https://boards.4channel.org/vg/thread/492044652",
        "dqg": "https://boards.4channel.org/vg/thread/491853316",
        "drg": "https://boards.4channel.org/vg/thread/492410859",
        "dsg": "https://boards.4channel.org/vg/thread/492133995",
        "e7g": "https://boards.4channel.org/vg/thread/492143426",
        "eftg": "https://boards.4channel.org/vg/thread/492166018",
        "egg": "https://boards.4channel.org/vg/thread/492499493",
        "emugen": "https://boards.4channel.org/vg/thread/491322090",
        "enlg": "https://boards.4channel.org/vg/thread/491796020",
        "eog": "https://boards.4channel.org/vg/thread/491678334",
        "erg": "https://boards.4channel.org/vg/thread/492418956",
        "esg": "https://boards.4channel.org/vg/thread/492140914",
        "exeg": "https://boards.4channel.org/vg/thread/491941427",
        "feg": "https://boards.4channel.org/vg/thread/492476112",
        "feh": "https://boards.4channel.org/vg/thread/492075709",
        "ffg": "https://boards.4channel.org/vg/thread/492345441",
        "fg": "https://boards.4channel.org/vg/thread/492436179",
        "fgg": "https://boards.4channel.org/vg/thread/492451780",
        "fgoalter": "https://boards.4channel.org/vg/thread/492489167",
        "fgog": "https://boards.4channel.org/vg/thread/492437849",
        "fng": "https://boards.4channel.org/vg/thread/492474175",
        "fog": "https://boards.4channel.org/vg/thread/492115387",
        "forza": "https://boards.4channel.org/vg/thread/492385739",
        "funkg": "https://boards.4channel.org/vg/thread/492448294",
        "gbfg": "https://boards.4channel.org/vg/thread/492492135",
        "gbp": "https://boards.4channel.org/vg/thread/492393057",
        "gbpen": "https://boards.4channel.org/vg/thread/492405729",
        "gbvsg": "https://boards.4channel.org/vg/thread/492460393",
        "gfg": "https://boards.4channel.org/vg/thread/492459039",
        "ggg": "https://boards.4channel.org/vg/thread/492467223",
        "gig": "https://boards.4channel.org/vg/thread/492488278",
        "gsg": "https://boards.4channel.org/vg/thread/492225971",
        "gtag": "https://boards.4channel.org/vg/thread/492171854",
        "gw2g": "https://boards.4channel.org/vg/thread/492386265",
        "haniho": "https://boards.4channel.org/vg/thread/492065534",
        "hbg": "https://boards.4channel.org/vg/thread/490904012",
        "hdg": "https://boards.4channel.org/vg/thread/492415587",
        "hg": "https://boards.4channel.org/vg/thread/492401590",
        "hgg2d": "https://boards.4channel.org/vg/thread/492455990",
        "hig": "https://boards.4channel.org/vg/thread/492274778",
        "horg": "https://boards.4channel.org/vg/thread/492467738",
        "hpgg": "https://boards.4channel.org/vg/thread/492368062",
        "hsg": "https://boards.4channel.org/vg/thread/491830239",
        "hsrg": "https://boards.4channel.org/vg/thread/492476149",
        "indie": "https://boards.4channel.org/vg/thread/492372768",
        "ink": "https://boards.4channel.org/vg/thread/492383675",
        "kdg": "https://boards.4channel.org/vg/thread/492134781",
        "keng": "https://boards.4channel.org/vg/thread/492338419",
        "kfg": "https://boards.4channel.org/vg/thread/490724776",
        "khg": "https://boards.4channel.org/vg/thread/491968435",
        "ksg": "https://boards.4channel.org/vg/thread/491675590",
        "lcg": "https://boards.4channel.org/vg/thread/492482153",
        "lisg": "https://boards.4channel.org/vg/thread/491735764",
        "llsifg": "https://boards.4channel.org/vg/thread/492329070",
        "lolg": "https://boards.4channel.org/vg/thread/492456770",
        "mcg": "https://boards.4channel.org/vg/thread/492354310",
        "melty": "https://boards.4channel.org/vg/thread/491066859",
        "mggg": "https://boards.4channel.org/vg/thread/491896630",
        "mhg": "https://boards.4channel.org/vg/thread/492433751",
        "mhurg": "https://boards.4channel.org/vg/thread/491367781",
        "mjg": "https://boards.4channel.org/vg/thread/492487837",
        "mmcg": "https://boards.4channel.org/vg/thread/492334474",
        "mmg": "https://boards.4channel.org/vg/thread/492334236",
        "msg": "https://boards.4channel.org/vg/thread/492513219",
        "mtgag": "https://boards.4channel.org/vg/thread/492140243",
        "mvsg": "https://boards.4channel.org/vg/thread/492333224",
        "neog": "https://boards.4channel.org/vg/thread/491981102",
        "nepgen": "https://boards.4channel.org/vg/thread/492108564",
        "nikg": "https://boards.4channel.org/vg/thread/492481198",
        "omg": "https://boards.4channel.org/vg/thread/490892148",
        "omog": "https://boards.4channel.org/vg/thread/492390798",
        "opg": "https://boards.4channel.org/vg/thread/491589030",
        "osg": "https://boards.4channel.org/vg/thread/492481670",
        "owg": "https://boards.4channel.org/vg/thread/492424129",
        "pal": "https://boards.4channel.org/vg/thread/490859593",
        "pcrg": "https://boards.4channel.org/vg/thread/492324243",
        "pg": "https://boards.4channel.org/vg/thread/492465561",
        "pgr": "https://boards.4channel.org/vg/thread/492483262",
        "pmg": "https://boards.4channel.org/vg/thread/492207492",
        "pmmm": "https://boards.4channel.org/vg/thread/491759518",
        "poeg": "https://boards.4channel.org/vg/thread/492475157",
        "ppg": "https://boards.4channel.org/vg/thread/492009668",
        "psg": "https://boards.4channel.org/vg/thread/491973818",
        "pso2g": "https://boards.4channel.org/vg/thread/492281591",
        "ptng": "https://boards.4channel.org/vg/thread/492341996",
        "rdg": "https://boards.4channel.org/vg/thread/491600619",
        "revue": "https://boards.4channel.org/vg/thread/490563238",
        "rlg": "https://boards.4channel.org/vg/thread/492173341",
        "rog": "https://boards.4channel.org/vg/thread/492484156",
        "rsg": "https://boards.4channel.org/vg/thread/491395367",
        "rwg": "https://boards.4channel.org/vg/thread/492467889",
        "scg": "https://boards.4channel.org/vg/thread/491696465",
        "sdvg": "https://boards.4channel.org/vg/thread/492377471",
        "sfg": "https://boards.4channel.org/vg/thread/492423921",
        "sg": "https://boards.4channel.org/vg/thread/492353927",
        "sgg": "https://boards.4channel.org/vg/thread/491863749",
        "simg": "https://boards.4channel.org/vg/thread/490524480",
        "skg": "https://boards.4channel.org/vg/thread/491825042",
        "slg": "https://boards.4channel.org/vg/thread/492194674",
        "smbg": "https://boards.4channel.org/vg/thread/492228151",
        "smtg": "https://boards.4channel.org/vg/thread/492285773",
        "snap": "https://boards.4channel.org/vg/thread/492354448",
        "snowg": "https://boards.4channel.org/vg/thread/492489848",
        "socg": "https://boards.4channel.org/vg/thread/492468386",
        "ss13g": "https://boards.4channel.org/vg/thread/492386958",
        "ssbg": "https://boards.4channel.org/vg/thread/491490809",
        "stag": "https://boards.4channel.org/vg/thread/492303905",
        "sthg": "https://boards.4channel.org/vg/thread/492483023",
        "svg": "https://boards.4channel.org/vg/thread/489444598",
        "tarog": "https://boards.4channel.org/vg/thread/492128848",
        "tekgen": "https://boards.4channel.org/vg/thread/492438565",
        "tesg": "https://boards.4channel.org/vg/thread/492402948",
        "tesog": "https://boards.4channel.org/vg/thread/492337084",
        "tf2g": "https://boards.4channel.org/vg/thread/492343847",
        "tfdg": "https://boards.4channel.org/vg/thread/492420264",
        "tg": "https://boards.4channel.org/vg/thread/492223221",
        "tsg": "https://boards.4channel.org/vg/thread/492072342",
        "twg": "https://boards.4channel.org/vg/thread/492486940",
        "twst": "https://boards.4channel.org/vg/thread/491437054",
        "uma": "https://boards.4channel.org/vg/thread/492379510",
        "utg": "https://boards.4channel.org/vg/thread/492450356",
        "vgt": "https://boards.4channel.org/vg/thread/492129564",
        "vn": "https://boards.4channel.org/vg/thread/492426406",
        "vrg": "https://boards.4channel.org/vg/thread/492430246",
        "wfg": "https://boards.4channel.org/vg/thread/492436640",
        "wowcg": "https://boards.4channel.org/vg/thread/491979194",
        "wowg": "https://boards.4channel.org/vg/thread/492469107",
        "wpsg": "https://boards.4channel.org/vg/thread/492221714",
        "wtg": "https://boards.4channel.org/vg/thread/492485282",
        "wuwa": "https://boards.4channel.org/vg/thread/492430750",
        "xivg": "https://boards.4channel.org/vg/thread/492489952",
        "zzz": "https://boards.4channel.org/vg/thread/492466008"
    },
    "vr": {
        "birth": "https://boards.4channel.org/vr/thread/11176256",
        "hbg": "https://boards.4channel.org/vr/thread/11184743",
        "hhg": "https://boards.4channel.org/vr/thread/11200020",
        "tg": "https://boards.4channel.org/vr/thread/11198620",
        "vr": "https://boards.4channel.org/vr/thread/11181784"
    }
}