{
    "biz": {
        "ag": "https://boards.4channel.org/biz/thread/56569361",
        "algo": "https://boards.4channel.org/biz/thread/56566858",
        "bbbyq": "https://boards.4channel.org/biz/thread/56551224",
        "biz": "https://boards.4channel.org/biz/thread/56573322",
        "cmmg": "https://boards.4channel.org/biz/thread/56562391",
        "gme": "https://boards.4channel.org/biz/thread/56558906",
        "pmg": "https://boards.4channel.org/biz/thread/56568266",
        "smg": "https://boards.4channel.org/biz/thread/56573193",
        "wfh": "https://boards.4channel.org/biz/thread/56571415",
        "xmr": "https://boards.4channel.org/biz/thread/56554410",
        "xsg": "https://boards.4channel.org/biz/thread/56565247"
    },
    "ck": {
        "ctg": "https://boards.4channel.org/ck/thread/19867743",
        "tea": "https://boards.4channel.org/ck/thread/19858407"
    },
    "fit": {
        "cbt": "https://boards.4channel.org/fit/thread/72711200",
        "fast": "https://boards.4channel.org/fit/thread/72721846",
        "fat": "https://boards.4channel.org/fit/thread/72725078",
        "fit": "https://boards.4channel.org/fit/thread/72729726",
        "fph": "https://boards.4channel.org/fit/thread/72719300",
        "plg": "https://boards.4channel.org/fit/thread/72724177",
        "run": "https://boards.4channel.org/fit/thread/72724092"
    },
    "g": {
        "aicg": "https://boards.4channel.org/g/thread/97136308",
        "bst": "https://boards.4channel.org/g/thread/97107240",
        "cpg": "https://boards.4channel.org/g/thread/97136182",
        "csg": "https://boards.4channel.org/g/thread/97074679",
        "cyb": "https://boards.4channel.org/g/thread/97138248",
        "de3": "https://boards.4channel.org/g/thread/97135440",
        "dmp": "https://boards.4channel.org/g/thread/97068921",
        "dpt": "https://boards.4channel.org/g/thread/97134781",
        "fglt": "https://boards.4channel.org/g/thread/97132548",
        "flet": "https://boards.4channel.org/g/thread/97125679",
        "fwt": "https://boards.4channel.org/g/thread/97088283",
        "gedg": "https://boards.4channel.org/g/thread/97078355",
        "hifi": "https://boards.4channel.org/g/thread/97132304",
        "hpg": "https://boards.4channel.org/g/thread/97129113",
        "hsg": "https://boards.4channel.org/g/thread/97126899",
        "iemg": "https://boards.4channel.org/g/thread/97131065",
        "lmg": "https://boards.4channel.org/g/thread/97134957",
        "mkg": "https://boards.4channel.org/g/thread/97127864",
        "pcbg": "https://boards.4channel.org/g/thread/97133344",
        "psg": "https://boards.4channel.org/g/thread/97123143",
        "ptg": "https://boards.4channel.org/g/thread/97116212",
        "sdg": "https://boards.4channel.org/g/thread/97135703",
        "spg": "https://boards.4channel.org/g/thread/97137546",
        "sqt": "https://boards.4channel.org/g/thread/97091468",
        "tpg": "https://boards.4channel.org/g/thread/97060082",
        "twg": "https://boards.4channel.org/g/thread/97121914",
        "wdg": "https://boards.4channel.org/g/thread/97113806"
    },
    "vg": {
        "2hug": "https://boards.4channel.org/vg/thread/452745167",
        "4ccg": "https://boards.4channel.org/vg/thread/453087381",
        "aa2g": "https://boards.4channel.org/vg/thread/453108560",
        "aceg": "https://boards.4channel.org/vg/thread/452971368",
        "acg": "https://boards.4channel.org/vg/thread/453124423",
        "agdg": "https://boards.4channel.org/vg/thread/453169879",
        "aids": "https://boards.4channel.org/vg/thread/453067745",
        "akg": "https://boards.4channel.org/vg/thread/453161862",
        "alg": "https://boards.4channel.org/vg/thread/453146746",
        "asg": "https://boards.4channel.org/vg/thread/452731887",
        "assg": "https://boards.4channel.org/vg/thread/453087738",
        "atg": "https://boards.4channel.org/vg/thread/453023507",
        "axg": "https://boards.4channel.org/vg/thread/452997868",
        "bag": "https://boards.4channel.org/vg/thread/453169376",
        "bd2g": "https://boards.4channel.org/vg/thread/453146919",
        "bdog": "https://boards.4channel.org/vg/thread/452836759",
        "bgg": "https://boards.4channel.org/vg/thread/453100286",
        "bowgen": "https://boards.4channel.org/vg/thread/452120236",
        "calg": "https://boards.4channel.org/vg/thread/453104720",
        "civ4xg": "https://boards.4channel.org/vg/thread/452957745",
        "codg": "https://boards.4channel.org/vg/thread/453091824",
        "coopg": "https://boards.4channel.org/vg/thread/453135573",
        "cp77g": "https://boards.4channel.org/vg/thread/453096293",
        "crpgg": "https://boards.4channel.org/vg/thread/452660974",
        "csg": "https://boards.4channel.org/vg/thread/453070373",
        "d2g": "https://boards.4channel.org/vg/thread/453117370",
        "d4g": "https://boards.4channel.org/vg/thread/452995313",
        "dadg": "https://boards.4channel.org/vg/thread/453177103",
        "dbg": "https://boards.4channel.org/vg/thread/452563030",
        "ddg": "https://boards.4channel.org/vg/thread/453067430",
        "ddlc": "https://boards.4channel.org/vg/thread/452442358",
        "dg": "https://boards.4channel.org/vg/thread/453167654",
        "digi": "https://boards.4channel.org/vg/thread/452939341",
        "dlsg": "https://boards.4channel.org/vg/thread/452728609",
        "dng": "https://boards.4channel.org/vg/thread/453071493",
        "doko": "https://boards.4channel.org/vg/thread/452651026",
        "domg": "https://boards.4channel.org/vg/thread/453093206",
        "dqg": "https://boards.4channel.org/vg/thread/452654009",
        "drg": "https://boards.4channel.org/vg/thread/453168346",
        "dsg": "https://boards.4channel.org/vg/thread/452912319",
        "e7g": "https://boards.4channel.org/vg/thread/452939329",
        "eftg": "https://boards.4channel.org/vg/thread/452146567",
        "egg": "https://boards.4channel.org/vg/thread/452810554",
        "emugen": "https://boards.4channel.org/vg/thread/452783212",
        "enlg": "https://boards.4channel.org/vg/thread/452709132",
        "eog": "https://boards.4channel.org/vg/thread/452115539",
        "erbsg": "https://boards.4channel.org/vg/thread/452278335",
        "erg": "https://boards.4channel.org/vg/thread/453049726",
        "esg": "https://boards.4channel.org/vg/thread/452192485",
        "exeg": "https://boards.4channel.org/vg/thread/453079317",
        "feg": "https://boards.4channel.org/vg/thread/453112335",
        "feh": "https://boards.4channel.org/vg/thread/453154334",
        "ffg": "https://boards.4channel.org/vg/thread/453124031",
        "fg": "https://boards.4channel.org/vg/thread/453136147",
        "fgg": "https://boards.4channel.org/vg/thread/453012485",
        "fgoalter": "https://boards.4channel.org/vg/thread/453157610",
        "fgog": "https://boards.4channel.org/vg/thread/453133626",
        "fng": "https://boards.4channel.org/vg/thread/453174851",
        "fog": "https://boards.4channel.org/vg/thread/452653163",
        "forza": "https://boards.4channel.org/vg/thread/452957718",
        "funkg": "https://boards.4channel.org/vg/thread/453097916",
        "gbfg": "https://boards.4channel.org/vg/thread/453163079",
        "gbp": "https://boards.4channel.org/vg/thread/452037775",
        "gbpen": "https://boards.4channel.org/vg/thread/452917337",
        "gfg": "https://boards.4channel.org/vg/thread/453173089",
        "ggg": "https://boards.4channel.org/vg/thread/452878780",
        "gig": "https://boards.4channel.org/vg/thread/453166283",
        "gsg": "https://boards.4channel.org/vg/thread/452458118",
        "gw2g": "https://boards.4channel.org/vg/thread/452665505",
        "haniho": "https://boards.4channel.org/vg/thread/452119260",
        "hbg": "https://boards.4channel.org/vg/thread/453137175",
        "hg": "https://boards.4channel.org/vg/thread/452925507",
        "hgg2d": "https://boards.4channel.org/vg/thread/453133073",
        "hig": "https://boards.4channel.org/vg/thread/453092425",
        "horg": "https://boards.4channel.org/vg/thread/452304504",
        "hpgg": "https://boards.4channel.org/vg/thread/453077650",
        "hrzg": "https://boards.4channel.org/vg/thread/452428736",
        "hsg": "https://boards.4channel.org/vg/thread/453085870",
        "hsrg": "https://boards.4channel.org/vg/thread/453163329",
        "htg": "https://boards.4channel.org/vg/thread/451018363",
        "idle": "https://boards.4channel.org/vg/thread/453171976",
        "indie": "https://boards.4channel.org/vg/thread/452922671",
        "ink": "https://boards.4channel.org/vg/thread/453089319",
        "kdg": "https://boards.4channel.org/vg/thread/452759360",
        "keng": "https://boards.4channel.org/vg/thread/452366747",
        "kfg": "https://boards.4channel.org/vg/thread/451631205",
        "khg": "https://boards.4channel.org/vg/thread/453154848",
        "ksg": "https://boards.4channel.org/vg/thread/452807727",
        "lag": "https://boards.4channel.org/vg/thread/452769013",
        "lcg": "https://boards.4channel.org/vg/thread/453146214",
        "lgg": "https://boards.4channel.org/vg/thread/452415547",
        "lisg": "https://boards.4channel.org/vg/thread/452760325",
        "llsifg": "https://boards.4channel.org/vg/thread/453100993",
        "lolg": "https://boards.4channel.org/vg/thread/453132713",
        "lotfg": "https://boards.4channel.org/vg/thread/452731273",
        "mbg": "https://boards.4channel.org/vg/thread/452870182",
        "mcg": "https://boards.4channel.org/vg/thread/452748081",
        "mdg": "https://boards.4channel.org/vg/thread/453151419",
        "melty": "https://boards.4channel.org/vg/thread/452734053",
        "mggg": "https://boards.4channel.org/vg/thread/453056617",
        "mhg": "https://boards.4channel.org/vg/thread/453090445",
        "mhurg": "https://boards.4channel.org/vg/thread/452880785",
        "mjg": "https://boards.4channel.org/vg/thread/453096678",
        "mkg": "https://boards.4channel.org/vg/thread/452831613",
        "mmcg": "https://boards.4channel.org/vg/thread/452505457",
        "mmg": "https://boards.4channel.org/vg/thread/453122782",
        "msg": "https://boards.4channel.org/vg/thread/453149232",
        "mtgag": "https://boards.4channel.org/vg/thread/452854124",
        "neog": "https://boards.4channel.org/vg/thread/452758239",
        "nepgen": "https://boards.4channel.org/vg/thread/452662759",
        "nikg": "https://boards.4channel.org/vg/thread/453156983",
        "nisg": "https://boards.4channel.org/vg/thread/452462084",
        "nrg": "https://boards.4channel.org/vg/thread/451823292",
        "omg": "https://boards.4channel.org/vg/thread/452515368",
        "omog": "https://boards.4channel.org/vg/thread/452967989",
        "opg": "https://boards.4channel.org/vg/thread/452365071",
        "osg": "https://boards.4channel.org/vg/thread/453071656",
        "owg": "https://boards.4channel.org/vg/thread/453133925",
        "pcrg": "https://boards.4channel.org/vg/thread/453160552",
        "pg": "https://boards.4channel.org/vg/thread/453145630",
        "pgr": "https://boards.4channel.org/vg/thread/452922924",
        "phsg": "https://boards.4channel.org/vg/thread/453033696",
        "pmg": "https://boards.4channel.org/vg/thread/453045165",
        "pmmm": "https://boards.4channel.org/vg/thread/452972661",
        "poeg": "https://boards.4channel.org/vg/thread/452965016",
        "psg": "https://boards.4channel.org/vg/thread/453088169",
        "pso2g": "https://boards.4channel.org/vg/thread/452729626",
        "ptng": "https://boards.4channel.org/vg/thread/453172629",
        "rdg": "https://boards.4channel.org/vg/thread/451833241",
        "revue": "https://boards.4channel.org/vg/thread/452151863",
        "rlg": "https://boards.4channel.org/vg/thread/452263026",
        "rog": "https://boards.4channel.org/vg/thread/452986273",
        "rsg": "https://boards.4channel.org/vg/thread/452755641",
        "rwg": "https://boards.4channel.org/vg/thread/452959980",
        "sfg": "https://boards.4channel.org/vg/thread/453145604",
        "sg": "https://boards.4channel.org/vg/thread/452909559",
        "sgg": "https://boards.4channel.org/vg/thread/451925883",
        "shmupg": "https://boards.4channel.org/vg/thread/452525435",
        "simg": "https://boards.4channel.org/vg/thread/452552516",
        "skg": "https://boards.4channel.org/vg/thread/453066697",
        "slg": "https://boards.4channel.org/vg/thread/452803807",
        "smbg": "https://boards.4channel.org/vg/thread/453176721",
        "smtg": "https://boards.4channel.org/vg/thread/452761662",
        "snap": "https://boards.4channel.org/vg/thread/453115556",
        "snowg": "https://boards.4channel.org/vg/thread/453161650",
        "ss13g": "https://boards.4channel.org/vg/thread/452929081",
        "ssbg": "https://boards.4channel.org/vg/thread/452200472",
        "stag": "https://boards.4channel.org/vg/thread/452962259",
        "sthg": "https://boards.4channel.org/vg/thread/453131079",
        "svg": "https://boards.4channel.org/vg/thread/452124170",
        "tarog": "https://boards.4channel.org/vg/thread/451599063",
        "tekgen": "https://boards.4channel.org/vg/thread/453154973",
        "tesg": "https://boards.4channel.org/vg/thread/453126402",
        "tesog": "https://boards.4channel.org/vg/thread/452802751",
        "tf2g": "https://boards.4channel.org/vg/thread/453043743",
        "tfg": "https://boards.4channel.org/vg/thread/452754001",
        "tg": "https://boards.4channel.org/vg/thread/452196693",
        "tofg": "https://boards.4channel.org/vg/thread/453148886",
        "tsg": "https://boards.4channel.org/vg/thread/452705438",
        "turtleg": "https://boards.4channel.org/vg/thread/452743212",
        "twg": "https://boards.4channel.org/vg/thread/453027875",
        "twst": "https://boards.4channel.org/vg/thread/452482831",
        "uma": "https://boards.4channel.org/vg/thread/452710494",
        "utg": "https://boards.4channel.org/vg/thread/453156648",
        "vgt": "https://boards.4channel.org/vg/thread/451538234",
        "vn": "https://boards.4channel.org/vg/thread/453134993",
        "vrg": "https://boards.4channel.org/vg/thread/453173025",
        "wfg": "https://boards.4channel.org/vg/thread/452990671",
        "wowcg": "https://boards.4channel.org/vg/thread/453121736",
        "wowg": "https://boards.4channel.org/vg/thread/453152870",
        "wtg": "https://boards.4channel.org/vg/thread/453105992",
        "xgg": "https://boards.4channel.org/vg/thread/453042536",
        "xivg": "https://boards.4channel.org/vg/thread/453168068"
    },
    "vr": {
        "gbc": "https://boards.4channel.org/vr/thread/10381394",
        "hbg": "https://boards.4channel.org/vr/thread/10370498",
        "hhg": "https://boards.4channel.org/vr/thread/10380978",
        "vr": "https://boards.4channel.org/vr/thread/10375096",
        "win95": "https://boards.4channel.org/vr/thread/10384967"
    }
}