{
    "biz": {
        "bbbyq": "https://boards.4channel.org/biz/thread/55551824",
        "biz": "https://boards.4channel.org/biz/thread/55559569",
        "cmmg": "https://boards.4channel.org/biz/thread/55497561",
        "gme": "https://boards.4channel.org/biz/thread/55555377",
        "pmg": "https://boards.4channel.org/biz/thread/55553906",
        "smg": "https://boards.4channel.org/biz/thread/55554837",
        "xmr": "https://boards.4channel.org/biz/thread/55522408",
        "xsg": "https://boards.4channel.org/biz/thread/55555036"
    },
    "ck": {
        "ck": "https://boards.4channel.org/ck/thread/19491332",
        "ctg": "https://boards.4channel.org/ck/thread/19480770",
        "tea": "https://boards.4channel.org/ck/thread/19488920"
    },
    "fit": {
        "cbt": "https://boards.4channel.org/fit/thread/71606322",
        "cg": "https://boards.4channel.org/fit/thread/71588341",
        "fast": "https://boards.4channel.org/fit/thread/71603380",
        "fat": "https://boards.4channel.org/fit/thread/71605463",
        "fit": "https://boards.4channel.org/fit/thread/71605523",
        "fittion": "https://boards.4channel.org/fit/thread/71603870",
        "fph": "https://boards.4channel.org/fit/thread/71591503",
        "fraud": "https://boards.4channel.org/fit/thread/71594775",
        "plg": "https://boards.4channel.org/fit/thread/71595030",
        "run": "https://boards.4channel.org/fit/thread/71584148"
    },
    "g": {
        "adv": "https://boards.4channel.org/g/thread/94707876",
        "aicg": "https://boards.4channel.org/g/thread/94711634",
        "bst": "https://boards.4channel.org/g/thread/94668576",
        "csg": "https://boards.4channel.org/g/thread/94663049",
        "cyb": "https://boards.4channel.org/g/thread/94654978",
        "d7t": "https://boards.4channel.org/g/thread/94708829",
        "dmp": "https://boards.4channel.org/g/thread/94672339",
        "dpt": "https://boards.4channel.org/g/thread/94679114",
        "fglt": "https://boards.4channel.org/g/thread/94690398",
        "fwt": "https://boards.4channel.org/g/thread/94666814",
        "g": "https://boards.4channel.org/g/thread/94700360",
        "gedg": "https://boards.4channel.org/g/thread/94688309",
        "gr": "https://boards.4channel.org/g/thread/94713266",
        "hifi": "https://boards.4channel.org/g/thread/94709458",
        "hsg": "https://boards.4channel.org/g/thread/94658288",
        "iemg": "https://boards.4channel.org/g/thread/94688530",
        "let": "https://boards.4channel.org/g/thread/94704994",
        "lmg": "https://boards.4channel.org/g/thread/94710001",
        "mkg": "https://boards.4channel.org/g/thread/94666103",
        "psg": "https://boards.4channel.org/g/thread/94708034",
        "ptg": "https://boards.4channel.org/g/thread/94697408",
        "sdg": "https://boards.4channel.org/g/thread/94707401",
        "spg": "https://boards.4channel.org/g/thread/94662995",
        "sqt": "https://boards.4channel.org/g/thread/94681514",
        "tpg": "https://boards.4channel.org/g/thread/94708242",
        "twg": "https://boards.4channel.org/g/thread/94710692",
        "wdg": "https://boards.4channel.org/g/thread/94682366"
    },
    "vg": {
        "2hug": "https://boards.4channel.org/vg/thread/437192979",
        "4ccg": "https://boards.4channel.org/vg/thread/437538454",
        "aa2g": "https://boards.4channel.org/vg/thread/437414950",
        "aceg": "https://boards.4channel.org/vg/thread/437823402",
        "agdg": "https://boards.4channel.org/vg/thread/437870516",
        "agg": "https://boards.4channel.org/vg/thread/437772416",
        "aids": "https://boards.4channel.org/vg/thread/437824936",
        "akg": "https://boards.4channel.org/vg/thread/437874962",
        "alg": "https://boards.4channel.org/vg/thread/437875563",
        "asg": "https://boards.4channel.org/vg/thread/436398671",
        "assg": "https://boards.4channel.org/vg/thread/437911707",
        "atg": "https://boards.4channel.org/vg/thread/437554370",
        "axg": "https://boards.4channel.org/vg/thread/437887093",
        "bag": "https://boards.4channel.org/vg/thread/437843138",
        "bbrg": "https://boards.4channel.org/vg/thread/437893570",
        "bd2g": "https://boards.4channel.org/vg/thread/437902542",
        "bdog": "https://boards.4channel.org/vg/thread/437844510",
        "bgg": "https://boards.4channel.org/vg/thread/437875837",
        "bowgen": "https://boards.4channel.org/vg/thread/436907745",
        "bpg": "https://boards.4channel.org/vg/thread/437567782",
        "calg": "https://boards.4channel.org/vg/thread/437608642",
        "civ4xg": "https://boards.4channel.org/vg/thread/437781819",
        "codg": "https://boards.4channel.org/vg/thread/437823874",
        "coopg": "https://boards.4channel.org/vg/thread/437810869",
        "cp77g": "https://boards.4channel.org/vg/thread/437015829",
        "crpgg": "https://boards.4channel.org/vg/thread/437059609",
        "csg": "https://boards.4channel.org/vg/thread/437736320",
        "d2g": "https://boards.4channel.org/vg/thread/437752310",
        "d4g": "https://boards.4channel.org/vg/thread/437756714",
        "dbg": "https://boards.4channel.org/vg/thread/437309226",
        "ddg": "https://boards.4channel.org/vg/thread/437631540",
        "ddlc": "https://boards.4channel.org/vg/thread/437598946",
        "dg": "https://boards.4channel.org/vg/thread/437676536",
        "digi": "https://boards.4channel.org/vg/thread/437608419",
        "dlg": "https://boards.4channel.org/vg/thread/437514528",
        "dng": "https://boards.4channel.org/vg/thread/437875902",
        "domg": "https://boards.4channel.org/vg/thread/437821035",
        "dqg": "https://boards.4channel.org/vg/thread/437281195",
        "drg": "https://boards.4channel.org/vg/thread/437291321",
        "dsg": "https://boards.4channel.org/vg/thread/437665637",
        "e7g": "https://boards.4channel.org/vg/thread/437740494",
        "egg": "https://boards.4channel.org/vg/thread/437641980",
        "emugen": "https://boards.4channel.org/vg/thread/437679334",
        "enlg": "https://boards.4channel.org/vg/thread/437294924",
        "eog": "https://boards.4channel.org/vg/thread/437583497",
        "erg": "https://boards.4channel.org/vg/thread/437845746",
        "esg": "https://boards.4channel.org/vg/thread/437701605",
        "exeg": "https://boards.4channel.org/vg/thread/437635323",
        "feg": "https://boards.4channel.org/vg/thread/437820651",
        "feh": "https://boards.4channel.org/vg/thread/437776304",
        "ffg": "https://boards.4channel.org/vg/thread/437829314",
        "fg": "https://boards.4channel.org/vg/thread/437800567",
        "fgg": "https://boards.4channel.org/vg/thread/437832416",
        "fgoalter": "https://boards.4channel.org/vg/thread/437881752",
        "fgog": "https://boards.4channel.org/vg/thread/437877290",
        "fng": "https://boards.4channel.org/vg/thread/437658153",
        "fog": "https://boards.4channel.org/vg/thread/437890949",
        "forza": "https://boards.4channel.org/vg/thread/437253685",
        "funkg": "https://boards.4channel.org/vg/thread/437868292",
        "gbfg": "https://boards.4channel.org/vg/thread/437882676",
        "gbp": "https://boards.4channel.org/vg/thread/436631613",
        "gbpen": "https://boards.4channel.org/vg/thread/437761293",
        "gfg": "https://boards.4channel.org/vg/thread/437887402",
        "ggg": "https://boards.4channel.org/vg/thread/437883059",
        "gig": "https://boards.4channel.org/vg/thread/437883479",
        "gsg": "https://boards.4channel.org/vg/thread/437500253",
        "gtag": "https://boards.4channel.org/vg/thread/437113172",
        "gtg": "https://boards.4channel.org/vg/thread/437512576",
        "gum": "https://boards.4channel.org/vg/thread/437874535",
        "gw2g": "https://boards.4channel.org/vg/thread/437515740",
        "haniho": "https://boards.4channel.org/vg/thread/437620803",
        "hbg": "https://boards.4channel.org/vg/thread/437469116",
        "hg": "https://boards.4channel.org/vg/thread/437715592",
        "hgg2d": "https://boards.4channel.org/vg/thread/437855146",
        "hig": "https://boards.4channel.org/vg/thread/437835796",
        "horg": "https://boards.4channel.org/vg/thread/437074797",
        "hpgg": "https://boards.4channel.org/vg/thread/437815965",
        "hrzvigg": "https://boards.4channel.org/vg/thread/436651096",
        "hsg": "https://boards.4channel.org/vg/thread/437392263",
        "hsrg": "https://boards.4channel.org/vg/thread/437866874",
        "htg": "https://boards.4channel.org/vg/thread/437512075",
        "indie": "https://boards.4channel.org/vg/thread/437809676",
        "ink": "https://boards.4channel.org/vg/thread/437828778",
        "kdg": "https://boards.4channel.org/vg/thread/436456485",
        "keng": "https://boards.4channel.org/vg/thread/436802893",
        "kfg": "https://boards.4channel.org/vg/thread/437122391",
        "khg": "https://boards.4channel.org/vg/thread/437511778",
        "kjpg": "https://boards.4channel.org/vg/thread/437310587",
        "ksg": "https://boards.4channel.org/vg/thread/436801931",
        "lag": "https://boards.4channel.org/vg/thread/437834154",
        "lcg": "https://boards.4channel.org/vg/thread/437887126",
        "lisg": "https://boards.4channel.org/vg/thread/437109690",
        "llsifg": "https://boards.4channel.org/vg/thread/437636014",
        "lolg": "https://boards.4channel.org/vg/thread/437843251",
        "lozg": "https://boards.4channel.org/vg/thread/437859068",
        "mbg": "https://boards.4channel.org/vg/thread/436222497",
        "mcg": "https://boards.4channel.org/vg/thread/436679335",
        "mdg": "https://boards.4channel.org/vg/thread/437682928",
        "melty": "https://boards.4channel.org/vg/thread/437462224",
        "mggg": "https://boards.4channel.org/vg/thread/437836954",
        "mhg": "https://boards.4channel.org/vg/thread/437769718",
        "milsim": "https://boards.4channel.org/vg/thread/437567454",
        "mjg": "https://boards.4channel.org/vg/thread/437877342",
        "mmcg": "https://boards.4channel.org/vg/thread/437465332",
        "mmg": "https://boards.4channel.org/vg/thread/437845424",
        "msg": "https://boards.4channel.org/vg/thread/437809763",
        "mtgag": "https://boards.4channel.org/vg/thread/437641169",
        "neog": "https://boards.4channel.org/vg/thread/437601174",
        "nepgen": "https://boards.4channel.org/vg/thread/437205520",
        "nikg": "https://boards.4channel.org/vg/thread/437870857",
        "nisg": "https://boards.4channel.org/vg/thread/437638529",
        "nrg": "https://boards.4channel.org/vg/thread/436871745",
        "ocg": "https://boards.4channel.org/vg/thread/437232382",
        "omg": "https://boards.4channel.org/vg/thread/436923790",
        "omog": "https://boards.4channel.org/vg/thread/437612768",
        "opg": "https://boards.4channel.org/vg/thread/437712327",
        "osg": "https://boards.4channel.org/vg/thread/437831394",
        "owg": "https://boards.4channel.org/vg/thread/437794675",
        "pcrg": "https://boards.4channel.org/vg/thread/437815446",
        "pg": "https://boards.4channel.org/vg/thread/437838992",
        "pgr": "https://boards.4channel.org/vg/thread/437764887",
        "pmg": "https://boards.4channel.org/vg/thread/437611019",
        "pmmm": "https://boards.4channel.org/vg/thread/437884272",
        "poeg": "https://boards.4channel.org/vg/thread/437675525",
        "psg": "https://boards.4channel.org/vg/thread/437656136",
        "pso2g": "https://boards.4channel.org/vg/thread/437871041",
        "ptng": "https://boards.4channel.org/vg/thread/437785767",
        "revue": "https://boards.4channel.org/vg/thread/436823535",
        "rlg": "https://boards.4channel.org/vg/thread/437784107",
        "rsg": "https://boards.4channel.org/vg/thread/437513436",
        "rwg": "https://boards.4channel.org/vg/thread/437795047",
        "sfg": "https://boards.4channel.org/vg/thread/437882998",
        "sg": "https://boards.4channel.org/vg/thread/437756176",
        "sgg": "https://boards.4channel.org/vg/thread/437154471",
        "shmupg": "https://boards.4channel.org/vg/thread/437720296",
        "simg": "https://boards.4channel.org/vg/thread/436925110",
        "skg": "https://boards.4channel.org/vg/thread/437872908",
        "slg": "https://boards.4channel.org/vg/thread/437314716",
        "smbg": "https://boards.4channel.org/vg/thread/437378412",
        "smtg": "https://boards.4channel.org/vg/thread/437726195",
        "snap": "https://boards.4channel.org/vg/thread/437803857",
        "ss13g": "https://boards.4channel.org/vg/thread/437882171",
        "ssbg": "https://boards.4channel.org/vg/thread/437322714",
        "stag": "https://boards.4channel.org/vg/thread/437389502",
        "sthg": "https://boards.4channel.org/vg/thread/437848487",
        "svg": "https://boards.4channel.org/vg/thread/437796303",
        "swgg": "https://boards.4channel.org/vg/thread/437205609",
        "tarog": "https://boards.4channel.org/vg/thread/437365685",
        "tekgen": "https://boards.4channel.org/vg/thread/437650174",
        "tesg": "https://boards.4channel.org/vg/thread/437881970",
        "tesog": "https://boards.4channel.org/vg/thread/437090169",
        "tf2g": "https://boards.4channel.org/vg/thread/437813909",
        "tg": "https://boards.4channel.org/vg/thread/437683665",
        "tofg": "https://boards.4channel.org/vg/thread/437376382",
        "tosg": "https://boards.4channel.org/vg/thread/437715036",
        "tsg": "https://boards.4channel.org/vg/thread/437752171",
        "turtleg": "https://boards.4channel.org/vg/thread/437744909",
        "twg": "https://boards.4channel.org/vg/thread/437837485",
        "twst": "https://boards.4channel.org/vg/thread/437062637",
        "uma": "https://boards.4channel.org/vg/thread/437428995",
        "utg": "https://boards.4channel.org/vg/thread/437861042",
        "vgt": "https://boards.4channel.org/vg/thread/435961443",
        "vn": "https://boards.4channel.org/vg/thread/437828017",
        "vrg": "https://boards.4channel.org/vg/thread/437842865",
        "wfg": "https://boards.4channel.org/vg/thread/437789357",
        "wowcg": "https://boards.4channel.org/vg/thread/437775248",
        "wowg": "https://boards.4channel.org/vg/thread/437879021",
        "wpsg": "https://boards.4channel.org/vg/thread/437844954",
        "wtg": "https://boards.4channel.org/vg/thread/437824389",
        "xgg": "https://boards.4channel.org/vg/thread/437674029",
        "xivg": "https://boards.4channel.org/vg/thread/437889962"
    },
    "vr": {
        "crt": "https://boards.4channel.org/vr/thread/10067798",
        "hbg": "https://boards.4channel.org/vr/thread/10053007",
        "hhg": "https://boards.4channel.org/vr/thread/10060769",
        "vr": "https://boards.4channel.org/vr/thread/10067893",
        "y2k": "https://boards.4channel.org/vr/thread/10055171"
    }
}