{
    "biz": {
        "aaa": "https://boards.4channel.org/biz/thread/55964137",
        "aiatc": "https://boards.4channel.org/biz/thread/55964841",
        "avax": "https://boards.4channel.org/biz/thread/55963753",
        "bbbyq": "https://boards.4channel.org/biz/thread/55960401",
        "biz": "https://boards.4channel.org/biz/thread/55965168",
        "cmmg": "https://boards.4channel.org/biz/thread/55926401",
        "gjg": "https://boards.4channel.org/biz/thread/55947025",
        "gme": "https://boards.4channel.org/biz/thread/55963055",
        "kg": "https://boards.4channel.org/biz/thread/55959832",
        "pmg": "https://boards.4channel.org/biz/thread/55948152",
        "smg": "https://boards.4channel.org/biz/thread/55963296",
        "tlcg": "https://boards.4channel.org/biz/thread/55940437",
        "xmr": "https://boards.4channel.org/biz/thread/55950497",
        "xsg": "https://boards.4channel.org/biz/thread/55965207"
    },
    "ck": {
        "bbg": "https://boards.4channel.org/ck/thread/19646097",
        "ck": "https://boards.4channel.org/ck/thread/19648816",
        "ctg": "https://boards.4channel.org/ck/thread/19637298",
        "tea": "https://boards.4channel.org/ck/thread/19625866"
    },
    "fit": {
        "2": "https://boards.4channel.org/fit/thread/72082247",
        "beenz": "https://boards.4channel.org/fit/thread/72080220",
        "fast": "https://boards.4channel.org/fit/thread/72058415",
        "fat": "https://boards.4channel.org/fit/thread/72073279",
        "fig": "https://boards.4channel.org/fit/thread/72082155",
        "fit": "https://boards.4channel.org/fit/thread/72041438",
        "fph": "https://boards.4channel.org/fit/thread/72068667",
        "pht": "https://boards.4channel.org/fit/thread/72082251",
        "plg": "https://boards.4channel.org/fit/thread/72062131",
        "run": "https://boards.4channel.org/fit/thread/72063507",
        "strength": "https://boards.4channel.org/fit/thread/72084114"
    },
    "g": {
        "aicg": "https://boards.4channel.org/g/thread/95665343",
        "aosg": "https://boards.4channel.org/g/thread/95627342",
        "bst": "https://boards.4channel.org/g/thread/95661750",
        "comfy": "https://boards.4channel.org/g/thread/95661676",
        "csg": "https://boards.4channel.org/g/thread/95653626",
        "cyb": "https://boards.4channel.org/g/thread/95560164",
        "dmp": "https://boards.4channel.org/g/thread/95622339",
        "dpt": "https://boards.4channel.org/g/thread/95639824",
        "fglt": "https://boards.4channel.org/g/thread/95619736",
        "flet": "https://boards.4channel.org/g/thread/95637079",
        "fwt": "https://boards.4channel.org/g/thread/95605810",
        "g": "https://boards.4channel.org/g/thread/95666121",
        "gedg": "https://boards.4channel.org/g/thread/95599094",
        "hifi": "https://boards.4channel.org/g/thread/95615371",
        "hpg": "https://boards.4channel.org/g/thread/95641001",
        "hsg": "https://boards.4channel.org/g/thread/95574795",
        "iemg": "https://boards.4channel.org/g/thread/95647298",
        "lmg": "https://boards.4channel.org/g/thread/95660669",
        "mkg": "https://boards.4channel.org/g/thread/95664523",
        "pcbg": "https://boards.4channel.org/g/thread/95659974",
        "psg": "https://boards.4channel.org/g/thread/95643779",
        "ptg": "https://boards.4channel.org/g/thread/95659984",
        "sdg": "https://boards.4channel.org/g/thread/95660298",
        "spg": "https://boards.4channel.org/g/thread/95659452",
        "sqt": "https://boards.4channel.org/g/thread/95638697",
        "tpg": "https://boards.4channel.org/g/thread/95603447",
        "twg": "https://boards.4channel.org/g/thread/95656171",
        "wdg": "https://boards.4channel.org/g/thread/95654437"
    },
    "vg": {
        "2hug": "https://boards.4channel.org/vg/thread/442744460",
        "4ccg": "https://boards.4channel.org/vg/thread/443788172",
        "aa2g": "https://boards.4channel.org/vg/thread/443945495",
        "aceg": "https://boards.4channel.org/vg/thread/443643692",
        "acg": "https://boards.4channel.org/vg/thread/444175579",
        "agdg": "https://boards.4channel.org/vg/thread/444116832",
        "aids": "https://boards.4channel.org/vg/thread/444076065",
        "akg": "https://boards.4channel.org/vg/thread/444173751",
        "alg": "https://boards.4channel.org/vg/thread/444139789",
        "asg": "https://boards.4channel.org/vg/thread/444034224",
        "assg": "https://boards.4channel.org/vg/thread/444126217",
        "atg": "https://boards.4channel.org/vg/thread/443104607",
        "axg": "https://boards.4channel.org/vg/thread/444100580",
        "bag": "https://boards.4channel.org/vg/thread/444173036",
        "bbrg": "https://boards.4channel.org/vg/thread/443905331",
        "bd2g": "https://boards.4channel.org/vg/thread/443530716",
        "bdog": "https://boards.4channel.org/vg/thread/444148523",
        "bgg": "https://boards.4channel.org/vg/thread/444166926",
        "bowgen": "https://boards.4channel.org/vg/thread/441727382",
        "bpg": "https://boards.4channel.org/vg/thread/442416905",
        "calg": "https://boards.4channel.org/vg/thread/443362030",
        "civ4xg": "https://boards.4channel.org/vg/thread/443790289",
        "codg": "https://boards.4channel.org/vg/thread/443983276",
        "coopg": "https://boards.4channel.org/vg/thread/443746373",
        "cp77g": "https://boards.4channel.org/vg/thread/443524669",
        "crpgg": "https://boards.4channel.org/vg/thread/443613454",
        "csg": "https://boards.4channel.org/vg/thread/443768868",
        "d2g": "https://boards.4channel.org/vg/thread/444122224",
        "d4g": "https://boards.4channel.org/vg/thread/444029454",
        "dadg": "https://boards.4channel.org/vg/thread/444074275",
        "dbg": "https://boards.4channel.org/vg/thread/443280948",
        "ddlc": "https://boards.4channel.org/vg/thread/443851587",
        "dg": "https://boards.4channel.org/vg/thread/444181161",
        "digi": "https://boards.4channel.org/vg/thread/443520980",
        "dlg": "https://boards.4channel.org/vg/thread/443637381",
        "dng": "https://boards.4channel.org/vg/thread/444073604",
        "domg": "https://boards.4channel.org/vg/thread/444074114",
        "dqg": "https://boards.4channel.org/vg/thread/443533585",
        "drg": "https://boards.4channel.org/vg/thread/444044932",
        "dsg": "https://boards.4channel.org/vg/thread/443998883",
        "e7g": "https://boards.4channel.org/vg/thread/443937175",
        "eftg": "https://boards.4channel.org/vg/thread/444015749",
        "egg": "https://boards.4channel.org/vg/thread/443876075",
        "emugen": "https://boards.4channel.org/vg/thread/443675782",
        "enlg": "https://boards.4channel.org/vg/thread/444014129",
        "eog": "https://boards.4channel.org/vg/thread/443884701",
        "erbsg": "https://boards.4channel.org/vg/thread/443947134",
        "erg": "https://boards.4channel.org/vg/thread/444137142",
        "esg": "https://boards.4channel.org/vg/thread/443069105",
        "exeg": "https://boards.4channel.org/vg/thread/444061005",
        "feg": "https://boards.4channel.org/vg/thread/444148908",
        "feh": "https://boards.4channel.org/vg/thread/444067623",
        "ffg": "https://boards.4channel.org/vg/thread/443891995",
        "fg": "https://boards.4channel.org/vg/thread/443964135",
        "fgg": "https://boards.4channel.org/vg/thread/444066448",
        "fgoalter": "https://boards.4channel.org/vg/thread/444159967",
        "fgog": "https://boards.4channel.org/vg/thread/444165436",
        "fng": "https://boards.4channel.org/vg/thread/444166737",
        "fog": "https://boards.4channel.org/vg/thread/443873130",
        "forza": "https://boards.4channel.org/vg/thread/444010435",
        "funkg": "https://boards.4channel.org/vg/thread/444109216",
        "gbfg": "https://boards.4channel.org/vg/thread/444158118",
        "gbp": "https://boards.4channel.org/vg/thread/443260282",
        "gbpen": "https://boards.4channel.org/vg/thread/444169687",
        "gfg": "https://boards.4channel.org/vg/thread/444176020",
        "ggg": "https://boards.4channel.org/vg/thread/444151750",
        "gig": "https://boards.4channel.org/vg/thread/444139542",
        "gsg": "https://boards.4channel.org/vg/thread/443782967",
        "gtag": "https://boards.4channel.org/vg/thread/444009204",
        "gum": "https://boards.4channel.org/vg/thread/442926513",
        "gw2g": "https://boards.4channel.org/vg/thread/444101638",
        "haniho": "https://boards.4channel.org/vg/thread/443889562",
        "hbg": "https://boards.4channel.org/vg/thread/444087843",
        "hg": "https://boards.4channel.org/vg/thread/443842361",
        "hgg2d": "https://boards.4channel.org/vg/thread/444159828",
        "hig": "https://boards.4channel.org/vg/thread/444003865",
        "horg": "https://boards.4channel.org/vg/thread/443090360",
        "hpgg": "https://boards.4channel.org/vg/thread/444176636",
        "hrzg": "https://boards.4channel.org/vg/thread/444131031",
        "hsg": "https://boards.4channel.org/vg/thread/444004004",
        "hsrg": "https://boards.4channel.org/vg/thread/444177393",
        "htg": "https://boards.4channel.org/vg/thread/443306732",
        "indie": "https://boards.4channel.org/vg/thread/444007943",
        "ink": "https://boards.4channel.org/vg/thread/444178583",
        "kdg": "https://boards.4channel.org/vg/thread/443722576",
        "keng": "https://boards.4channel.org/vg/thread/444165002",
        "kfg": "https://boards.4channel.org/vg/thread/442806383",
        "khg": "https://boards.4channel.org/vg/thread/443726162",
        "ksg": "https://boards.4channel.org/vg/thread/442492928",
        "lag": "https://boards.4channel.org/vg/thread/443929948",
        "lcg": "https://boards.4channel.org/vg/thread/444148389",
        "lisg": "https://boards.4channel.org/vg/thread/443942140",
        "llsifg": "https://boards.4channel.org/vg/thread/444129000",
        "lolg": "https://boards.4channel.org/vg/thread/444166173",
        "lozg": "https://boards.4channel.org/vg/thread/444089137",
        "mbg": "https://boards.4channel.org/vg/thread/443735450",
        "mcg": "https://boards.4channel.org/vg/thread/443533680",
        "mdg": "https://boards.4channel.org/vg/thread/443557036",
        "melty": "https://boards.4channel.org/vg/thread/442259729",
        "mggg": "https://boards.4channel.org/vg/thread/443747305",
        "mhg": "https://boards.4channel.org/vg/thread/444107472",
        "milsim": "https://boards.4channel.org/vg/thread/444186568",
        "mjg": "https://boards.4channel.org/vg/thread/444165303",
        "mkg": "https://boards.4channel.org/vg/thread/444086245",
        "mmcg": "https://boards.4channel.org/vg/thread/443602791",
        "mmg": "https://boards.4channel.org/vg/thread/444148980",
        "msg": "https://boards.4channel.org/vg/thread/443812241",
        "mtgag": "https://boards.4channel.org/vg/thread/443814508",
        "neog": "https://boards.4channel.org/vg/thread/444012706",
        "nepgen": "https://boards.4channel.org/vg/thread/443769942",
        "nikg": "https://boards.4channel.org/vg/thread/444170925",
        "nisg": "https://boards.4channel.org/vg/thread/442158268",
        "nrg": "https://boards.4channel.org/vg/thread/442302250",
        "omg": "https://boards.4channel.org/vg/thread/443288063",
        "omog": "https://boards.4channel.org/vg/thread/443947113",
        "opg": "https://boards.4channel.org/vg/thread/444153002",
        "owg": "https://boards.4channel.org/vg/thread/444170330",
        "pcrg": "https://boards.4channel.org/vg/thread/444156515",
        "pg": "https://boards.4channel.org/vg/thread/444069851",
        "pgr": "https://boards.4channel.org/vg/thread/443983616",
        "pmg": "https://boards.4channel.org/vg/thread/444118610",
        "pmmm": "https://boards.4channel.org/vg/thread/443800531",
        "poeg": "https://boards.4channel.org/vg/thread/444100032",
        "psg": "https://boards.4channel.org/vg/thread/443802895",
        "pso2g": "https://boards.4channel.org/vg/thread/444107854",
        "ptng": "https://boards.4channel.org/vg/thread/443465201",
        "revue": "https://boards.4channel.org/vg/thread/443871527",
        "rlg": "https://boards.4channel.org/vg/thread/443976210",
        "rsg": "https://boards.4channel.org/vg/thread/444050396",
        "rwg": "https://boards.4channel.org/vg/thread/444128434",
        "sfg": "https://boards.4channel.org/vg/thread/444116040",
        "sg": "https://boards.4channel.org/vg/thread/443849247",
        "sgg": "https://boards.4channel.org/vg/thread/444168802",
        "shmupg": "https://boards.4channel.org/vg/thread/443774108",
        "simg": "https://boards.4channel.org/vg/thread/443768763",
        "skg": "https://boards.4channel.org/vg/thread/444161051",
        "slg": "https://boards.4channel.org/vg/thread/443314778",
        "smbg": "https://boards.4channel.org/vg/thread/443871193",
        "smtg": "https://boards.4channel.org/vg/thread/444043357",
        "snapg": "https://boards.4channel.org/vg/thread/444112060",
        "snowg": "https://boards.4channel.org/vg/thread/444145410",
        "ss13g": "https://boards.4channel.org/vg/thread/443943391",
        "ssbg": "https://boards.4channel.org/vg/thread/443769085",
        "stag": "https://boards.4channel.org/vg/thread/444168778",
        "sthg": "https://boards.4channel.org/vg/thread/444151235",
        "svg": "https://boards.4channel.org/vg/thread/443433870",
        "tarog": "https://boards.4channel.org/vg/thread/442424456",
        "tekgen": "https://boards.4channel.org/vg/thread/443969862",
        "tesg": "https://boards.4channel.org/vg/thread/443991054",
        "tesog": "https://boards.4channel.org/vg/thread/442899540",
        "tf2g": "https://boards.4channel.org/vg/thread/444166957",
        "tg": "https://boards.4channel.org/vg/thread/443029419",
        "tofg": "https://boards.4channel.org/vg/thread/443992409",
        "tsg": "https://boards.4channel.org/vg/thread/443396728",
        "turtleg": "https://boards.4channel.org/vg/thread/443821932",
        "twg": "https://boards.4channel.org/vg/thread/444170040",
        "twst": "https://boards.4channel.org/vg/thread/443723779",
        "uma": "https://boards.4channel.org/vg/thread/443932648",
        "utg": "https://boards.4channel.org/vg/thread/444133472",
        "vgt": "https://boards.4channel.org/vg/thread/443406603",
        "vn": "https://boards.4channel.org/vg/thread/444142280",
        "vrg": "https://boards.4channel.org/vg/thread/443967364",
        "wfg": "https://boards.4channel.org/vg/thread/444096082",
        "wowcg": "https://boards.4channel.org/vg/thread/444086219",
        "wowg": "https://boards.4channel.org/vg/thread/444121005",
        "wpsg": "https://boards.4channel.org/vg/thread/443266294",
        "wtg": "https://boards.4channel.org/vg/thread/444112995",
        "xgg": "https://boards.4channel.org/vg/thread/444027094",
        "xivg": "https://boards.4channel.org/vg/thread/444173274"
    },
    "vr": {
        "hbg": "https://boards.4channel.org/vr/thread/10169487",
        "vr": "https://boards.4channel.org/vr/thread/10175701"
    }
}